comdab/__init__.py
comdab/build.py
comdab/compare.py
comdab/exceptions.py
comdab/main.py
comdab/path.py
comdab/py.typed
comdab/report.py
comdab/source.py
comdab/utils.py
comdab/models/__init__.py
comdab/models/base.py
comdab/models/column.py
comdab/models/constraint.py
comdab/models/custom_type.py
comdab/models/function.py
comdab/models/index.py
comdab/models/schema.py
comdab/models/sequence.py
comdab/models/table.py
comdab/models/trigger.py
comdab/models/type.py
comdab/models/view.py
comdab/specific/__init__.py
comdab/specific/postgresql/__init__.py
comdab/specific/postgresql/build.py
comdab/specific/postgresql/custom_types.py
comdab/specific/postgresql/exclude_constraints.py
comdab/specific/postgresql/functions.py
comdab/specific/postgresql/sequences.py
comdab/specific/postgresql/triggers.py
comdab/specific/postgresql/views.py
comdab-0.3.0.dist-info/METADATA
comdab-0.3.0.dist-info/WHEEL
comdab-0.3.0.dist-info/licenses/LICENSE
comdab-0.3.0.dist-info/RECORD
