Metadata-Version: 2.4
Name: comdab
Version: 0.3.0
Summary: Compare Database Schemas
Project-URL: Homepage, https://github.com/loic-simon/comdab
Project-URL: Documentation, https://comdab.readthedocs.io/en/latest
Project-URL: Repository, https://github.com/loic-simon/comdab
Project-URL: Issues, https://github.com/loic-simon/comdab/issues
Author-email: Loïc Simon <loic.simon@espci.org>
License-File: LICENSE
Classifier: Development Status :: 4 - Beta
Classifier: Intended Audience :: Developers
Classifier: Programming Language :: Python :: 3
Classifier: Programming Language :: Python :: 3.12
Classifier: Programming Language :: Python :: 3.13
Classifier: Programming Language :: Python :: 3.14
Classifier: Topic :: Database
Classifier: Typing :: Typed
Requires-Python: >=3.12
Requires-Dist: pydantic>=2.0
Requires-Dist: sqlalchemy>=2.0
